snmpsim_data/__init__.py
snmpsim_data/data/UPS/apc-7902b.snmprec
snmpsim_data/data/UPS/apc-8641.snmprec
snmpsim_data/data/UPS/apc-8932.snmprec
snmpsim_data/data/UPS/eastpower-istars-swv053.snmprec.bz2
snmpsim_data/data/UPS/eaton-93e-80.snmprec.bz2
snmpsim_data/data/UPS/eaton-9px-partial.snmprec.bz2
snmpsim_data/data/UPS/emerson-network-power.snmprec.bz2
snmpsim_data/data/UPS/huawei-gse200m.snmprec.bz2
snmpsim_data/data/UPS/ingrasys-power-switch.snmprec.bz2
snmpsim_data/data/UPS/juniper-ac.snmprec.bz2
snmpsim_data/data/UPS/phoenixtec-power.snmprec.bz2
snmpsim_data/data/UPS/vertiv-power.snmprec.bz2
snmpsim_data/data/bmc/hp-onboard-administrator.snmprec.bz2
snmpsim_data/data/camera/hikvision-network-video-recorder.snmprec.bz2
snmpsim_data/data/camera/hikvision.snmprec.bz2
snmpsim_data/data/camera/samsung-ipolis.snmprec.bz2
snmpsim_data/data/camera/semac-ipcam-500.snmprec.bz2
snmpsim_data/data/camera/wds-ips-1022.snmprec.bz2
snmpsim_data/data/cloud/arista-dcs-7150s-52-cl.snmprec.bz2
snmpsim_data/data/iot/geist-temperature-sensor.snmprec
snmpsim_data/data/network/appliance/cisco-controller.snmprec.bz2
snmpsim_data/data/network/appliance/cisco-ucs-6100-k9.snmprec.bz2
snmpsim_data/data/network/appliance/cisco-ucs-6100.snmprec.bz2
snmpsim_data/data/network/appliance/cisco-unknown-01.snmprec.bz2
snmpsim_data/data/network/appliance/empirical-hw-mgmt.snmprec.bz2
snmpsim_data/data/network/appliance/huawei-ism.snmprec.bz2
snmpsim_data/data/network/appliance/infosec-nsae-6500.snmprec.bz2
snmpsim_data/data/network/appliance/meru-networks-controller.snmprec.bz2
snmpsim_data/data/network/appliance/network-research-squid.snmprec.bz2
snmpsim_data/data/network/appliance/nsfocus-ads.snmprec.bz2
snmpsim_data/data/network/appliance/tripplite-poweralert.snmprec
snmpsim_data/data/network/appliance/ucdavis-sic.snmprec.bz2
snmpsim_data/data/network/appliance/vss-monitoring-optimizer-2400-span.snmprec.bz2
snmpsim_data/data/network/firewall/clavister-amaranten.snmprec.bz2
snmpsim_data_lextudio-1.0.0.dist-info/LICENSE.txt
snmpsim_data_lextudio-1.0.0.dist-info/METADATA
snmpsim_data_lextudio-1.0.0.dist-info/WHEEL
snmpsim_data_lextudio-1.0.0.dist-info/entry_points.txt
snmpsim_data_lextudio-1.0.0.dist-info/RECORD
